{
    "gridWidth": 6,
    "gridHeight": 6,
    "playerStartPosition": {
        "x": 5,
        "y": 2
    },
    "levelType": 0,
    "flagPosition": {
        "x": 0,
        "y": 0
    },
    "goldPerStar": 4,
    "starThresholds": [
        80.0,
        90.0,
        100.0
    ],
    "specificTileSetups": [
        {
            "position": {
                "x": 5,
                "y": 3
            },
            "type": 2,
            "grassLayers": 1,
            "visualVariantIndex": 0,
            "deadTreeStrength": 1,
            "pairedHolePosition": {
                "x": 0,
                "y": 0
            },
            "spreadTimer": 3
        },
        {
            "position": {
                "x": 3,
                "y": 2
            },
            "type": 2,
            "grassLayers": 1,
            "visualVariantIndex": 0,
            "deadTreeStrength": 1,
            "pairedHolePosition": {
                "x": 0,
                "y": 0
            },
            "spreadTimer": 3
        },
        {
            "position": {
                "x": 3,
                "y": 1
            },
            "type": 2,
            "grassLayers": 1,
            "visualVariantIndex": 0,
            "deadTreeStrength": 1,
            "pairedHolePosition": {
                "x": 0,
                "y": 0
            },
            "spreadTimer": 3
        },
        {
            "position": {
                "x": 5,
                "y": 0
            },
            "type": 2,
            "grassLayers": 1,
            "visualVariantIndex": 0,
            "deadTreeStrength": 1,
            "pairedHolePosition": {
                "x": 0,
                "y": 0
            },
            "spreadTimer": 3
        },
        {
            "position": {
                "x": 1,
                "y": 4
            },
            "type": 6,
            "grassLayers": 1,
            "visualVariantIndex": 0,
            "deadTreeStrength": 1,
            "pairedHolePosition": {
                "x": 0,
                "y": 0
            },
            "spreadTimer": 3
        },
        {
            "position": {
                "x": 4,
                "y": 4
            },
            "type": 0,
            "grassLayers": 1,
            "visualVariantIndex": 0,
            "deadTreeStrength": 1,
            "pairedHolePosition": {
                "x": 0,
                "y": 0
            },
            "spreadTimer": 3
        },
        {
            "position": {
                "x": 3,
                "y": 3
            },
            "type": 0,
            "grassLayers": 2,
            "visualVariantIndex": 0,
            "deadTreeStrength": 1,
            "pairedHolePosition": {
                "x": 0,
                "y": 0
            },
            "spreadTimer": 3
        },
        {
            "position": {
                "x": 3,
                "y": 0
            },
            "type": 0,
            "grassLayers": 2,
            "visualVariantIndex": 0,
            "deadTreeStrength": 1,
            "pairedHolePosition": {
                "x": 0,
                "y": 0
            },
            "spreadTimer": 3
        },
        {
            "position": {
                "x": 3,
                "y": 4
            },
            "type": 0,
            "grassLayers": 1,
            "visualVariantIndex": 0,
            "deadTreeStrength": 1,
            "pairedHolePosition": {
                "x": 0,
                "y": 0
            },
            "spreadTimer": 3
        },
        {
            "position": {
                "x": 2,
                "y": 0
            },
            "type": 0,
            "grassLayers": 2,
            "visualVariantIndex": 0,
            "deadTreeStrength": 1,
            "pairedHolePosition": {
                "x": 0,
                "y": 0
            },
            "spreadTimer": 3
        },
        {
            "position": {
                "x": 2,
                "y": 4
            },
            "type": 0,
            "grassLayers": 1,
            "visualVariantIndex": 0,
            "deadTreeStrength": 1,
            "pairedHolePosition": {
                "x": 0,
                "y": 0
            },
            "spreadTimer": 3
        },
        {
            "position": {
                "x": 2,
                "y": 2
            },
            "type": 0,
            "grassLayers": 2,
            "visualVariantIndex": 0,
            "deadTreeStrength": 1,
            "pairedHolePosition": {
                "x": 0,
                "y": 0
            },
            "spreadTimer": 3
        },
        {
            "position": {
                "x": 1,
                "y": 3
            },
            "type": 0,
            "grassLayers": 1,
            "visualVariantIndex": 0,
            "deadTreeStrength": 1,
            "pairedHolePosition": {
                "x": 0,
                "y": 0
            },
            "spreadTimer": 3
        },
        {
            "position": {
                "x": 2,
                "y": 1
            },
            "type": 0,
            "grassLayers": 1,
            "visualVariantIndex": 0,
            "deadTreeStrength": 1,
            "pairedHolePosition": {
                "x": 0,
                "y": 0
            },
            "spreadTimer": 3
        },
        {
            "position": {
                "x": 1,
                "y": 0
            },
            "type": 0,
            "grassLayers": 1,
            "visualVariantIndex": 0,
            "deadTreeStrength": 1,
            "pairedHolePosition": {
                "x": 0,
                "y": 0
            },
            "spreadTimer": 3
        },
        {
            "position": {
                "x": 1,
                "y": 2
            },
            "type": 0,
            "grassLayers": 1,
            "visualVariantIndex": 0,
            "deadTreeStrength": 1,
            "pairedHolePosition": {
                "x": 0,
                "y": 0
            },
            "spreadTimer": 3
        },
        {
            "position": {
                "x": 0,
                "y": 3
            },
            "type": 0,
            "grassLayers": 3,
            "visualVariantIndex": 0,
            "deadTreeStrength": 1,
            "pairedHolePosition": {
                "x": 0,
                "y": 0
            },
            "spreadTimer": 3
        },
        {
            "position": {
                "x": 0,
                "y": 0
            },
            "type": 0,
            "grassLayers": 1,
            "visualVariantIndex": 0,
            "deadTreeStrength": 1,
            "pairedHolePosition": {
                "x": 0,
                "y": 0
            },
            "spreadTimer": 3
        },
        {
            "position": {
                "x": 1,
                "y": 5
            },
            "type": 0,
            "grassLayers": 1,
            "visualVariantIndex": 0,
            "deadTreeStrength": 1,
            "pairedHolePosition": {
                "x": 0,
                "y": 0
            },
            "spreadTimer": 3
        },
        {
            "position": {
                "x": 0,
                "y": 5
            },
            "type": 0,
            "grassLayers": 2,
            "visualVariantIndex": 0,
            "deadTreeStrength": 1,
            "pairedHolePosition": {
                "x": 0,
                "y": 0
            },
            "spreadTimer": 3
        },
        {
            "position": {
                "x": 5,
                "y": 2
            },
            "type": 0,
            "grassLayers": 1,
            "visualVariantIndex": 0,
            "deadTreeStrength": 1,
            "pairedHolePosition": {
                "x": 0,
                "y": 0
            },
            "spreadTimer": 3
        },
        {
            "position": {
                "x": 5,
                "y": 1
            },
            "type": 0,
            "grassLayers": 1,
            "visualVariantIndex": 0,
            "deadTreeStrength": 1,
            "pairedHolePosition": {
                "x": 0,
                "y": 0
            },
            "spreadTimer": 3
        },
        {
            "position": {
                "x": 4,
                "y": 2
            },
            "type": 0,
            "grassLayers": 2,
            "visualVariantIndex": 0,
            "deadTreeStrength": 1,
            "pairedHolePosition": {
                "x": 0,
                "y": 0
            },
            "spreadTimer": 3
        },
        {
            "position": {
                "x": 4,
                "y": 1
            },
            "type": 0,
            "grassLayers": 2,
            "visualVariantIndex": 0,
            "deadTreeStrength": 1,
            "pairedHolePosition": {
                "x": 0,
                "y": 0
            },
            "spreadTimer": 3
        },
        {
            "position": {
                "x": 4,
                "y": 3
            },
            "type": 0,
            "grassLayers": 2,
            "visualVariantIndex": 0,
            "deadTreeStrength": 1,
            "pairedHolePosition": {
                "x": 0,
                "y": 0
            },
            "spreadTimer": 3
        },
        {
            "position": {
                "x": 4,
                "y": 0
            },
            "type": 0,
            "grassLayers": 1,
            "visualVariantIndex": 0,
            "deadTreeStrength": 1,
            "pairedHolePosition": {
                "x": 0,
                "y": 0
            },
            "spreadTimer": 3
        },
        {
            "position": {
                "x": 2,
                "y": 5
            },
            "type": 0,
            "grassLayers": 3,
            "visualVariantIndex": 0,
            "deadTreeStrength": 1,
            "pairedHolePosition": {
                "x": 0,
                "y": 0
            },
            "spreadTimer": 3
        },
        {
            "position": {
                "x": 2,
                "y": 3
            },
            "type": 0,
            "grassLayers": 3,
            "visualVariantIndex": 0,
            "deadTreeStrength": 1,
            "pairedHolePosition": {
                "x": 0,
                "y": 0
            },
            "spreadTimer": 3
        },
        {
            "position": {
                "x": 0,
                "y": 4
            },
            "type": 0,
            "grassLayers": 1,
            "visualVariantIndex": 0,
            "deadTreeStrength": 1,
            "pairedHolePosition": {
                "x": 0,
                "y": 0
            },
            "spreadTimer": 3
        },
        {
            "position": {
                "x": 3,
                "y": 5
            },
            "type": 2,
            "grassLayers": 1,
            "visualVariantIndex": 0,
            "deadTreeStrength": 1,
            "pairedHolePosition": {
                "x": 0,
                "y": 0
            },
            "spreadTimer": 3
        },
        {
            "position": {
                "x": 0,
                "y": 2
            },
            "type": 3,
            "grassLayers": 1,
            "visualVariantIndex": 1,
            "deadTreeStrength": 1,
            "pairedHolePosition": {
                "x": 0,
                "y": 0
            },
            "spreadTimer": 3
        },
        {
            "position": {
                "x": 0,
                "y": 1
            },
            "type": 0,
            "grassLayers": 1,
            "visualVariantIndex": 0,
            "deadTreeStrength": 1,
            "pairedHolePosition": {
                "x": 0,
                "y": 0
            },
            "spreadTimer": 3
        },
        {
            "position": {
                "x": 1,
                "y": 1
            },
            "type": 0,
            "grassLayers": 2,
            "visualVariantIndex": 0,
            "deadTreeStrength": 1,
            "pairedHolePosition": {
                "x": 0,
                "y": 0
            },
            "spreadTimer": 3
        },
        {
            "position": {
                "x": 4,
                "y": 5
            },
            "type": 0,
            "grassLayers": 1,
            "visualVariantIndex": 0,
            "deadTreeStrength": 1,
            "pairedHolePosition": {
                "x": 0,
                "y": 0
            },
            "spreadTimer": 3
        },
        {
            "position": {
                "x": 5,
                "y": 5
            },
            "type": 0,
            "grassLayers": 1,
            "visualVariantIndex": 0,
            "deadTreeStrength": 1,
            "pairedHolePosition": {
                "x": 0,
                "y": 0
            },
            "spreadTimer": 3
        },
        {
            "position": {
                "x": 5,
                "y": 4
            },
            "type": 0,
            "grassLayers": 1,
            "visualVariantIndex": 0,
            "deadTreeStrength": 1,
            "pairedHolePosition": {
                "x": 0,
                "y": 0
            },
            "spreadTimer": 3
        }
    ],
    "hasTutorial": false,
    "tutorialData": {
        "tutorialId": "",
        "text_CN": "",
        "text_EN": ""
    }
}